pystage_apt-0.4.data/data/LICENSE.txt
stage/ctrl_msg/__init__.py
stage/ctrl_msg/_base.py
stage/ctrl_msg/filterflippercontrol.py
stage/ctrl_msg/lasercontrol.py
stage/ctrl_msg/motorcontrol.py
stage/ctrl_msg/nanotrackcontrol.py
stage/ctrl_msg/piezocontrol.py
stage/ctrl_msg/quadcontrol.py
stage/ctrl_msg/solenoidcontrol.py
stage/ctrl_msg/systemcontrol.py
stage/ctrl_msg/teccontrol.py
stage/motor_ctrl/__init__.py
stage/motor_ctrl/stage_info.py
stage/motor_ini/core.py
stage/motor_ini/port.py
pystage_apt-0.4.dist-info/LICENSE.txt
pystage_apt-0.4.dist-info/METADATA
pystage_apt-0.4.dist-info/WHEEL
pystage_apt-0.4.dist-info/top_level.txt
pystage_apt-0.4.dist-info/RECORD
