Metadata-Version: 2.1
Name: pystage-apt
Version: 0.4
Summary: A python library for Thorlabs' APT single-channel controllers
Home-page: https://github.com/kzhao1228/pystage_apt
Author: Kaixiang Zhao
Author-email: kz1619@ic.ac.uk
License: MIT
Platform: Linux
Classifier: Intended Audience :: Science/Research
Classifier: License :: OSI Approved :: MIT License
Classifier: Programming Language :: Python :: 3
Classifier: Topic :: Scientific/Engineering
Classifier: Topic :: Software Development :: Libraries
Classifier: Topic :: System :: Hardware
Classifier: Operating System :: POSIX :: Linux
Requires-Python: >=3
Requires-Dist: pyusb (>=1.0.0a)
Requires-Dist: pyserial (>=2.7)
